{
  "project_info": {
    "project_number": "649568117891",
    "firebase_url": "https://jobsforyou-tamizha.firebaseio.com",
    "project_id": "jobsforyou-tamizha",
    "storage_bucket": "jobsforyou-tamizha.appspot.com"
  },
  "client": [
    {
      "client_info": {
        "mobilesdk_app_id": "1:649568117891:android:2b0f25275c5b3f1142e7b6",
        "android_client_info": {
          "package_name": "com.jobs.jobforyoutamizha"
        }
      },
      "oauth_client": [
        {
          "client_id": "649568117891-kujjs7mfmnd97m48ohutqbeufihrsnel.apps.googleusercontent.com",
          "client_type": 1,
          "android_info": {
            "package_name": "com.jobs.jobforyoutamizha",
            "certificate_hash": "8dd94d0fc8353c58bd23a67d6b483f820d7cdb5b"
          }
        },
        {
          "client_id": "649568117891-g6m0do61tu1aknm74k58j5ahj739smof.apps.googleusercontent.com",
          "client_type": 1,
          "android_info": {
            "package_name": "com.jobs.jobforyoutamizha",
            "certificate_hash": "9462fa8f25314deec0692660707ba4048e73e248"
          }
        },
        {
          "client_id": "649568117891-kg6m16n6b3fevqvbdt5d3er2f6o22dee.apps.googleusercontent.com",
          "client_type": 3
        }
      ],
      "api_key": [
        {
          "current_key": "AIzaSyD-lbhby6rtdnSUOwG7PIyFF_3SOX4ymVc"
        }
      ],
      "services": {
        "appinvite_service": {
          "other_platform_oauth_client": [
            {
              "client_id": "649568117891-kg6m16n6b3fevqvbdt5d3er2f6o22dee.apps.googleusercontent.com",
              "client_type": 3
            }
          ]
        }
      },
      "admob_app_id": "ca-app-pub-1698473155677356~6155661924"
    }
  ],
  "configuration_version": "1"
}